Workbook

Sheet README
A1: Video Game Sales -- Portfolio Project
A2: Data analyst portfolio piece | Built in Excel (openpyxl + native pivot tables)
A4: Data Source
A5: "Video Game Sales with Ratings" -- Kaggle dataset by rush4ratio (Vgchartz sales data merged with Metacritic critic/user scores). https://www.kaggle.com/datasets/rush4ratio/video-game-sales-with-ratings
A6: Used in full: 16,717 titles, 1980-2020 (sparse before ~1994 and after 2016). Roughly half the titles have no Metacritic score -- left blank rather than zero-filled, and every AVERAGEIFS/SUMIFS formula in this workbook is checked to confirm it handles those blanks correctly rather than silently treating a missing score as a real value.
A8: Why this dataset
A9: Real-world messiness (missing review scores, a handful of duplicate title/platform rows, sparse tail years) without being chaotic -- a realistic test of whether formulas degrade gracefully instead of just looking right on clean rows.
A11: Technique Map
A12: Technique / Function | B12: Sheet | C12: Cell(s) | D12: Purpose
A13: Text concatenation (&) | B13: Raw Data | C13: Q2 (NamePlatformKey) | D13: Composite key for text-field lookups.
A14: SUMPRODUCT (row finder) | B14: Genre Insights | C14: F5:F16 | D14: Multiplies boolean + ROW() arrays to find a matching row without an array-entered formula.
A15: INDEX/MATCH | B15: Game Lookup | C15: C8:C11 | D15: Returns text fields (Genre, Publisher, Developer, Rating) for the selected title.
A16: SUMIFS (as a 2-criteria lookup) | B16: Game Lookup | C16: C12:C21 | D16: Returns numeric fields without needing a helper key.
A17: COUNTIF / COUNTIFS | B17: Game Lookup, Genre Insights | C17: various | D17: Counts matching rows; also flags 'No data' instead of a false 0.
A18: SUMIF / AVERAGEIFS | B18: Genre Insights, Sales Trends | C18: various | D18: Totals and averages grouped by Genre, Year, or Publisher.
A19: MAXIFS | B19: Genre Insights | C19: F5:F16 | D19: Finds each genre's single highest Global Sales figure, feeding the SUMPRODUCT row finder above.
A20: Native Pivot Table | B20: Genre Insights | C20: H4 | D20: Sum of Global Sales cross-tabbed by Genre x Rating.
A21: Scatter Chart | B21: Genre Insights | C21: below table | D21: Plots avg critic score vs. total sales, one point per genre.
A22: Line Chart | B22: Sales Trends | C22: F4 | D22: Industry-wide global sales by release year.
A23: Conditional formatting (color scale) | B23: Sales Trends | C23: C18:C27 | D23: Highlights top publishers by total sales.
A26: Tip: click any formula cell across this workbook -- cells with a small red corner marker have a comment explaining the technique used, in addition to this map.

Sheet Raw Data
A1: Name | B1: Platform | C1: Year_of_Release | D1: Genre | E1: Publisher | F1: NA_Sales | G1: EU_Sales | H1: JP_Sales | I1: Other_Sales | J1: Global_Sales | K1: Critic_Score | L1: Critic_Count | M1: User_Score | N1: User_Count | O1: Developer | P1: Rating | Q1: NamePlatformKey
A2: Wii Sports | B2: Wii | C2: 2006 | D2: Sports | E2: Nintendo | F2: 41.36 | G2: 28.96 | H2: 3.77 | I2: 8.45 | J2: 82.53 | K2: 76 | L2: 51 | M2: 8 | N2: 322 | O2: Nintendo | P2: E | Q2: =A2&"|"&B2 -> Wii Sports|Wii
A3: Super Mario Bros. | B3: NES | C3: 1985 | D3: Platform | E3: Nintendo | F3: 29.08 | G3: 3.58 | H3: 6.81 | I3: 0.77 | J3: 40.24 | Q3: =A3&"|"&B3 -> Super Mario Bros.|NES
A4: Mario Kart Wii | B4: Wii | C4: 2008 | D4: Racing | E4: Nintendo | F4: 15.68 | G4: 12.76 | H4: 3.79 | I4: 3.29 | J4: 35.52 | K4: 82 | L4: 73 | M4: 8.3 | N4: 709 | O4: Nintendo | P4: E | Q4: =A4&"|"&B4 -> Mario Kart Wii|Wii
A5: Wii Sports Resort | B5: Wii | C5: 2009 | D5: Sports | E5: Nintendo | F5: 15.61 | G5: 10.93 | H5: 3.28 | I5: 2.95 | J5: 32.77 | K5: 80 | L5: 73 | M5: 8 | N5: 192 | O5: Nintendo | P5: E | Q5: =A5&"|"&B5 -> Wii Sports Resort|Wii
A6: Pokemon Red/Pokemon Blue | B6: GB | C6: 1996 | D6: Role-Playing | E6: Nintendo | F6: 11.27 | G6: 8.89 | H6: 10.22 | I6: 1 | J6: 31.37 | Q6: =A6&"|"&B6 -> Pokemon Red/Pokemon Blue|GB
A7: Tetris | B7: GB | C7: 1989 | D7: Puzzle | E7: Nintendo | F7: 23.2 | G7: 2.26 | H7: 4.22 | I7: 0.58 | J7: 30.26 | Q7: =A7&"|"&B7 -> Tetris|GB
A8: New Super Mario Bros. | B8: DS | C8: 2006 | D8: Platform | E8: Nintendo | F8: 11.28 | G8: 9.14 | H8: 6.5 | I8: 2.88 | J8: 29.8 | K8: 89 | L8: 65 | M8: 8.5 | N8: 431 | O8: Nintendo | P8: E | Q8: =A8&"|"&B8 -> New Super Mario Bros.|DS
A9: Wii Play | B9: Wii | C9: 2006 | D9: Misc | E9: Nintendo | F9: 13.96 | G9: 9.18 | H9: 2.93 | I9: 2.84 | J9: 28.92 | K9: 58 | L9: 41 | M9: 6.6 | N9: 129 | O9: Nintendo | P9: E | Q9: =A9&"|"&B9 -> Wii Play|Wii
A10: New Super Mario Bros. Wii | B10: Wii | C10: 2009 | D10: Platform | E10: Nintendo | F10: 14.44 | G10: 6.94 | H10: 4.7 | I10: 2.24 | J10: 28.32 | K10: 87 | L10: 80 | M10: 8.4 | N10: 594 | O10: Nintendo | P10: E | Q10: =A10&"|"&B10 -> New Super Mario Bros. Wii|Wii
A11: Duck Hunt | B11: NES | C11: 1984 | D11: Shooter | E11: Nintendo | F11: 26.93 | G11: 0.63 | H11: 0.28 | I11: 0.47 | J11: 28.31 | Q11: =A11&"|"&B11 -> Duck Hunt|NES
A12: Nintendogs | B12: DS | C12: 2005 | D12: Simulation | E12: Nintendo | F12: 9.05 | G12: 10.95 | H12: 1.93 | I12: 2.74 | J12: 24.67 | Q12: =A12&"|"&B12 -> Nintendogs|DS
A13: Mario Kart DS | B13: DS | C13: 2005 | D13: Racing | E13: Nintendo | F13: 9.71 | G13: 7.47 | H13: 4.13 | I13: 1.9 | J13: 23.21 | K13: 91 | L13: 64 | M13: 8.6 | N13: 464 | O13: Nintendo | P13: E | Q13: =A13&"|"&B13 -> Mario Kart DS|DS
A14: Pokemon Gold/Pokemon Silver | B14: GB | C14: 1999 | D14: Role-Playing | E14: Nintendo | F14: 9 | G14: 6.18 | H14: 7.2 | I14: 0.71 | J14: 23.1 | Q14: =A14&"|"&B14 -> Pokemon Gold/Pokemon Silver|GB
A15: Wii Fit | B15: Wii | C15: 2007 | D15: Sports | E15: Nintendo | F15: 8.92 | G15: 8.03 | H15: 3.6 | I15: 2.15 | J15: 22.7 | K15: 80 | L15: 63 | M15: 7.7 | N15: 146 | O15: Nintendo | P15: E | Q15: =A15&"|"&B15 -> Wii Fit|Wii
A16: Kinect Adventures! | B16: X360 | C16: 2010 | D16: Misc | E16: Microsoft Game Studios | F16: 15 | G16: 4.89 | H16: 0.24 | I16: 1.69 | J16: 21.81 | K16: 61 | L16: 45 | M16: 6.3 | N16: 106 | O16: Good Science Studio | P16: E | Q16: =A16&"|"&B16 -> Kinect Adventures!|X360
A17: Wii Fit Plus | B17: Wii | C17: 2009 | D17: Sports | E17: Nintendo | F17: 9.01 | G17: 8.49 | H17: 2.53 | I17: 1.77 | J17: 21.79 | K17: 80 | L17: 33 | M17: 7.4 | N17: 52 | O17: Nintendo | P17: E | Q17: =A17&"|"&B17 -> Wii Fit Plus|Wii
A18: Grand Theft Auto V | B18: PS3 | C18: 2013 | D18: Action | E18: Take-Two Interactive | F18: 7.02 | G18: 9.09 | H18: 0.98 | I18: 3.96 | J18: 21.04 | K18: 97 | L18: 50 | M18: 8.2 | N18: 3994 | O18: Rockstar North | P18: M | Q18: =A18&"|"&B18 -> Grand Theft Auto V|PS3
A19: Grand Theft Auto: San Andreas | B19: PS2 | C19: 2004 | D19: Action | E19: Take-Two Interactive | F19: 9.43 | G19: 0.4 | H19: 0.41 | I19: 10.57 | J19: 20.81 | K19: 95 | L19: 80 | M19: 9 | N19: 1588 | O19: Rockstar North | P19: M | Q19: =A19&"|"&B19 -> Grand Theft Auto: San Andreas|PS2
A20: Super Mario World | B20: SNES | C20: 1990 | D20: Platform | E20: Nintendo | F20: 12.78 | G20: 3.75 | H20: 3.54 | I20: 0.55 | J20: 20.61 | Q20: =A20&"|"&B20 -> Super Mario World|SNES
A21: Brain Age: Train Your Brain in Minutes a Day | B21: DS | C21: 2005 | D21: Misc | E21: Nintendo | F21: 4.74 | G21: 9.2 | H21: 4.16 | I21: 2.04 | J21: 20.15 | K21: 77 | L21: 58 | M21: 7.9 | N21: 50 | O21: Nintendo | P21: E | Q21: =A21&"|"&B21 -> Brain Age: Train Your Brain in Minutes a Day|DS
A22: Pokemon Diamond/Pokemon Pearl | B22: DS | C22: 2006 | D22: Role-Playing | E22: Nintendo | F22: 6.38 | G22: 4.46 | H22: 6.04 | I22: 1.36 | J22: 18.25 | Q22: =A22&"|"&B22 -> Pokemon Diamond/Pokemon Pearl|DS
A23: Super Mario Land | B23: GB | C23: 1989 | D23: Platform | E23: Nintendo | F23: 10.83 | G23: 2.71 | H23: 4.18 | I23: 0.42 | J23: 18.14 | Q23: =A23&"|"&B23 -> Super Mario Land|GB
A24: Super Mario Bros. 3 | B24: NES | C24: 1988 | D24: Platform | E24: Nintendo | F24: 9.54 | G24: 3.44 | H24: 3.84 | I24: 0.46 | J24: 17.28 | Q24: =A24&"|"&B24 -> Super Mario Bros. 3|NES
A25: Grand Theft Auto V | B25: X360 | C25: 2013 | D25: Action | E25: Take-Two Interactive | F25: 9.66 | G25: 5.14 | H25: 0.06 | I25: 1.41 | J25: 16.27 | K25: 97 | L25: 58 | M25: 8.1 | N25: 3711 | O25: Rockstar North | P25: M | Q25: =A25&"|"&B25 -> Grand Theft Auto V|X360
A26: Grand Theft Auto: Vice City | B26: PS2 | C26: 2002 | D26: Action | E26: Take-Two Interactive | F26: 8.41 | G26: 5.49 | H26: 0.47 | I26: 1.78 | J26: 16.15 | K26: 95 | L26: 62 | M26: 8.7 | N26: 730 | O26: Rockstar North | P26: M | Q26: =A26&"|"&B26 -> Grand Theft Auto: Vice City|PS2
A27: Pokemon Ruby/Pokemon Sapphire | B27: GBA | C27: 2002 | D27: Role-Playing | E27: Nintendo | F27: 6.06 | G27: 3.9 | H27: 5.38 | I27: 0.5 | J27: 15.85 | Q27: =A27&"|"&B27 -> Pokemon Ruby/Pokemon Sapphire|GBA
A28: Brain Age 2: More Training in Minutes a Day | B28: DS | C28: 2005 | D28: Puzzle | E28: Nintendo | F28: 3.43 | G28: 5.35 | H28: 5.32 | I28: 1.18 | J28: 15.29 | K28: 77 | L28: 37 | M28: 7.1 | N28: 19 | O28: Nintendo | P28: E | Q28: =A28&"|"&B28 -> Brain Age 2: More Training in Minutes a Day|DS
A29: Pokemon Black/Pokemon White | B29: DS | C29: 2010 | D29: Role-Playing | E29: Nintendo | F29: 5.51 | G29: 3.17 | H29: 5.65 | I29: 0.8 | J29: 15.14 | Q29: =A29&"|"&B29 -> Pokemon Black/Pokemon White|DS
A30: Gran Turismo 3: A-Spec | B30: PS2 | C30: 2001 | D30: Racing | E30: Sony Computer Entertainment | F30: 6.85 | G30: 5.09 | H30: 1.87 | I30: 1.16 | J30: 14.98 | K30: 95 | L30: 54 | M30: 8.4 | N30: 314 | O30: Polyphony Digital | P30: E | Q30: =A30&"|"&B30 -> Gran Turismo 3: A-Spec|PS2
A31: Call of Duty: Modern Warfare 3 | B31: X360 | C31: 2011 | D31: Shooter | E31: Activision | F31: 9.04 | G31: 4.24 | H31: 0.13 | I31: 1.32 | J31: 14.73 | K31: 88 | L31: 81 | M31: 3.4 | N31: 8713 | O31: Infinity Ward, Sledgehammer Games | P31: M | Q31: =A31&"|"&B31 -> Call of Duty: Modern Warfare 3|X360
A32: Pokémon Yellow: Special Pikachu Edition | B32: GB | C32: 1998 | D32: Role-Playing | E32: Nintendo | F32: 5.89 | G32: 5.04 | H32: 3.12 | I32: 0.59 | J32: 14.64 | Q32: =A32&"|"&B32 -> Pokémon Yellow: Special Pikachu Edition|GB
A33: Call of Duty: Black Ops 3 | B33: PS4 | C33: 2015 | D33: Shooter | E33: Activision | F33: 6.03 | G33: 5.86 | H33: 0.36 | I33: 2.38 | J33: 14.63 | Q33: =A33&"|"&B33 -> Call of Duty: Black Ops 3|PS4
A34: Call of Duty: Black Ops | B34: X360 | C34: 2010 | D34: Shooter | E34: Activision | F34: 9.7 | G34: 3.68 | H34: 0.11 | I34: 1.13 | J34: 14.61 | K34: 87 | L34: 89 | M34: 6.3 | N34: 1454 | O34: Treyarch | P34: M | Q34: =A34&"|"&B34 -> Call of Duty: Black Ops|X360
A35: Pokemon X/Pokemon Y | B35: 3DS | C35: 2013 | D35: Role-Playing | E35: Nintendo | F35: 5.28 | G35: 4.19 | H35: 4.35 | I35: 0.78 | J35: 14.6 | Q35: =A35&"|"&B35 -> Pokemon X/Pokemon Y|3DS
A36: Call of Duty: Black Ops II | B36: PS3 | C36: 2012 | D36: Shooter | E36: Activision | F36: 4.99 | G36: 5.73 | H36: 0.65 | I36: 2.42 | J36: 13.79 | K36: 83 | L36: 21 | M36: 5.3 | N36: 922 | O36: Treyarch | P36: M | Q36: =A36&"|"&B36 -> Call of Duty: Black Ops II|PS3
A37: Call of Duty: Black Ops II | B37: X360 | C37: 2012 | D37: Shooter | E37: Activision | F37: 8.25 | G37: 4.24 | H37: 0.07 | I37: 1.12 | J37: 13.67 | K37: 83 | L37: 73 | M37: 4.8 | N37: 2256 | O37: Treyarch | P37: M | Q37: =A37&"|"&B37 -> Call of Duty: Black Ops II|X360
A38: Call of Duty: Modern Warfare 2 | B38: X360 | C38: 2009 | D38: Shooter | E38: Activision | F38: 8.52 | G38: 3.59 | H38: 0.08 | I38: 1.28 | J38: 13.47 | K38: 94 | L38: 100 | M38: 6.3 | N38: 2698 | O38: Infinity Ward | P38: M | Q38: =A38&"|"&B38 -> Call of Duty: Modern Warfare 2|X360
A39: Call of Duty: Modern Warfare 3 | B39: PS3 | C39: 2011 | D39: Shooter | E39: Activision | F39: 5.54 | G39: 5.73 | H39: 0.49 | I39: 1.57 | J39: 13.32 | K39: 88 | L39: 39 | M39: 3.2 | N39: 5234 | O39: Infinity Ward, Sledgehammer Games | P39: M | Q39: =A39&"|"&B39 -> Call of Duty: Modern Warfare 3|PS3
A40: Grand Theft Auto III | B40: PS2 | C40: 2001 | D40: Action | E40: Take-Two Interactive | F40: 6.99 | G40: 4.51 | H40: 0.3 | I40: 1.3 | J40: 13.1 | K40: 97 | L40: 56 | M40: 8.5 | N40: 664 | O40: DMA Design | P40: M | Q40: =A40&"|"&B40 -> Grand Theft Auto III|PS2
A41: Super Smash Bros. Brawl | B41: Wii | C41: 2008 | D41: Fighting | E41: Nintendo | F41: 6.62 | G41: 2.55 | H41: 2.66 | I41: 1.01 | J41: 12.84 | K41: 93 | L41: 81 | M41: 8.9 | N41: 1662 | O41: Game Arts | P41: T | Q41: =A41&"|"&B41 -> Super Smash Bros. Brawl|Wii
A42: Mario Kart 7 | B42: 3DS | C42: 2011 | D42: Racing | E42: Nintendo | F42: 5.03 | G42: 4.02 | H42: 2.69 | I42: 0.91 | J42: 12.66 | K42: 85 | L42: 73 | M42: 8.2 | N42: 632 | O42: Retro Studios, Entertainment Analysis & Development Division | P42: E | Q42: =A42&"|"&B42 -> Mario Kart 7|3DS
A43: Call of Duty: Black Ops | B43: PS3 | C43: 2010 | D43: Shooter | E43: Activision | F43: 5.99 | G43: 4.37 | H43: 0.48 | I43: 1.79 | J43: 12.63 | K43: 88 | L43: 58 | M43: 6.4 | N43: 1094 | O43: Treyarch | P43: M | Q43: =A43&"|"&B43 -> Call of Duty: Black Ops|PS3
A44: Grand Theft Auto V | B44: PS4 | C44: 2014 | D44: Action | E44: Take-Two Interactive | F44: 3.96 | G44: 6.31 | H44: 0.38 | I44: 1.97 | J44: 12.61 | K44: 97 | L44: 66 | M44: 8.3 | N44: 2899 | O44: Rockstar North | P44: M | Q44: =A44&"|"&B44 -> Grand Theft Auto V|PS4
A45: Animal Crossing: Wild World | B45: DS | C45: 2005 | D45: Simulation | E45: Nintendo | F45: 2.5 | G45: 3.45 | H45: 5.33 | I45: 0.86 | J45: 12.13 | K45: 86 | L45: 57 | M45: 8.7 | N45: 242 | O45: Nintendo | P45: E | Q45: =A45&"|"&B45 -> Animal Crossing: Wild World|DS
A46: Halo 3 | B46: X360 | C46: 2007 | D46: Shooter | E46: Microsoft Game Studios | F46: 7.97 | G46: 2.81 | H46: 0.13 | I46: 1.21 | J46: 12.12 | K46: 94 | L46: 86 | M46: 7.8 | N46: 4100 | O46: Bungie Software, Bungie | P46: M | Q46: =A46&"|"&B46 -> Halo 3|X360
A47: Super Mario 64 | B47: N64 | C47: 1996 | D47: Platform | E47: Nintendo | F47: 6.91 | G47: 2.85 | H47: 1.91 | I47: 0.23 | J47: 11.89 | Q47: =A47&"|"&B47 -> Super Mario 64|N64
A48: Pokemon HeartGold/Pokemon SoulSilver | B48: DS | C48: 2009 | D48: Action | E48: Nintendo | F48: 4.34 | G48: 2.71 | H48: 3.96 | I48: 0.76 | J48: 11.77 | Q48: =A48&"|"&B48 -> Pokemon HeartGold/Pokemon SoulSilver|DS
A49: Pokemon Omega Ruby/Pokemon Alpha Sapphire | B49: 3DS | C49: 2014 | D49: Role-Playing | E49: Nintendo | F49: 4.35 | G49: 3.49 | H49: 3.1 | I49: 0.74 | J49: 11.68 | Q49: =A49&"|"&B49 -> Pokemon Omega Ruby/Pokemon Alpha Sapphire|3DS
A50: Gran Turismo 4 | B50: PS2 | C50: 2004 | D50: Racing | E50: Sony Computer Entertainment | F50: 3.01 | G50: 0.01 | H50: 1.1 | I50: 7.53 | J50: 11.66 | K50: 89 | L50: 74 | M50: 8.5 | N50: 272 | O50: Polyphony Digital | P50: E | Q50: =A50&"|"&B50 -> Gran Turismo 4|PS2
A51: Super Mario Galaxy | B51: Wii | C51: 2007 | D51: Platform | E51: Nintendo | F51: 6.06 | G51: 3.35 | H51: 1.2 | I51: 0.74 | J51: 11.35 | K51: 97 | L51: 73 | M51: 8.9 | N51: 2147 | O51: Nintendo | P51: E | Q51: =A51&"|"&B51 -> Super Mario Galaxy|Wii
A52: Super Mario Land 2: 6 Golden Coins | B52: GB | C52: 1992 | D52: Adventure | E52: Nintendo | F52: 6.16 | G52: 2.04 | H52: 2.69 | I52: 0.29 | J52: 11.18 | Q52: =A52&"|"&B52 -> Super Mario Land 2: 6 Golden Coins|GB
A53: Grand Theft Auto IV | B53: X360 | C53: 2008 | D53: Action | E53: Take-Two Interactive | F53: 6.76 | G53: 3.07 | H53: 0.14 | I53: 1.03 | J53: 11.01 | K53: 98 | L53: 86 | M53: 7.9 | N53: 2951 | O53: Rockstar North | P53: M | Q53: =A53&"|"&B53 -> Grand Theft Auto IV|X360
A54: Gran Turismo | B54: PS | C54: 1997 | D54: Racing | E54: Sony Computer Entertainment | F54: 4.02 | G54: 3.87 | H54: 2.54 | I54: 0.52 | J54: 10.95 | K54: 96 | L54: 16 | M54: 8.7 | N54: 138 | O54: Polyphony Digital | P54: E | Q54: =A54&"|"&B54 -> Gran Turismo|PS
A55: Super Mario 3D Land | B55: 3DS | C55: 2011 | D55: Platform | E55: Nintendo | F55: 4.89 | G55: 3 | H55: 2.14 | I55: 0.78 | J55: 10.81 | K55: 90 | L55: 82 | M55: 8.4 | N55: 921 | O55: Nintendo | P55: E | Q55: =A55&"|"&B55 -> Super Mario 3D Land|3DS
A56: Gran Turismo 5 | B56: PS3 | C56: 2010 | D56: Racing | E56: Sony Computer Entertainment | F56: 2.96 | G56: 4.82 | H56: 0.81 | I56: 2.11 | J56: 10.7 | K56: 84 | L56: 82 | M56: 7.5 | N56: 1112 | O56: Polyphony Digital | P56: E | Q56: =A56&"|"&B56 -> Gran Turismo 5|PS3
A57: Call of Duty: Modern Warfare 2 | B57: PS3 | C57: 2009 | D57: Shooter | E57: Activision | F57: 4.99 | G57: 3.64 | H57: 0.38 | I57: 1.6 | J57: 10.6 | K57: 94 | L57: 67 | M57: 6.3 | N57: 2073 | O57: Infinity Ward | P57: M | Q57: =A57&"|"&B57 -> Call of Duty: Modern Warfare 2|PS3
A58: Super Mario All-Stars | B58: SNES | C58: 1993 | D58: Platform | E58: Nintendo | F58: 5.99 | G58: 2.15 | H58: 2.12 | I58: 0.29 | J58: 10.55 | Q58: =A58&"|"&B58 -> Super Mario All-Stars|SNES
A59: Grand Theft Auto IV | B59: PS3 | C59: 2008 | D59: Action | E59: Take-Two Interactive | F59: 4.76 | G59: 3.69 | H59: 0.44 | I59: 1.61 | J59: 10.5 | K59: 98 | L59: 64 | M59: 7.5 | N59: 2833 | O59: Rockstar North | P59: M | Q59: =A59&"|"&B59 -> Grand Theft Auto IV|PS3
A60: Pokemon FireRed/Pokemon LeafGreen | B60: GBA | C60: 2004 | D60: Role-Playing | E60: Nintendo | F60: 4.34 | G60: 2.65 | H60: 3.15 | I60: 0.35 | J60: 10.49 | Q60: =A60&"|"&B60 -> Pokemon FireRed/Pokemon LeafGreen|GBA
A61: Super Mario 64 | B61: DS | C61: 2004 | D61: Platform | E61: Nintendo | F61: 5.01 | G61: 3.07 | H61: 1.25 | I61: 0.97 | J61: 10.3 | Q61: =A61&"|"&B61 -> Super Mario 64|DS
A62: Call of Duty: Ghosts | B62: X360 | C62: 2013 | D62: Shooter | E62: Activision | F62: 6.73 | G62: 2.56 | H62: 0.04 | I62: 0.91 | J62: 10.25 | K62: 73 | L62: 29 | M62: 2.6 | N62: 2117 | O62: Infinity Ward | P62: M | Q62: =A62&"|"&B62 -> Call of Duty: Ghosts|X360
A63: Just Dance 3 | B63: Wii | C63: 2011 | D63: Misc | E63: Ubisoft | F63: 5.95 | G63: 3.11 | H63: 0 | I63: 1.06 | J63: 10.12 | K63: 74 | L63: 15 | M63: 7.8 | N63: 16 | O63: Ubisoft | P63: E10+ | Q63: =A63&"|"&B63 -> Just Dance 3|Wii
A64: New Super Mario Bros. 2 | B64: 3DS | C64: 2012 | D64: Platform | E64: Nintendo | F64: 3.66 | G64: 3.14 | H64: 2.47 | I64: 0.63 | J64: 9.9 | K64: 78 | L64: 70 | M64: 7.2 | N64: 424 | O64: Nintendo | P64: E | Q64: =A64&"|"&B64 -> New Super Mario Bros. 2|3DS
A65: Mario Kart 64 | B65: N64 | C65: 1996 | D65: Racing | E65: Nintendo | F65: 5.55 | G65: 1.94 | H65: 2.23 | I65: 0.15 | J65: 9.87 | Q65: =A65&"|"&B65 -> Mario Kart 64|N64
A66: Halo: Reach | B66: X360 | C66: 2010 | D66: Shooter | E66: Microsoft Game Studios | F66: 7.04 | G66: 1.95 | H66: 0.08 | I66: 0.79 | J66: 9.86 | K66: 91 | L66: 99 | M66: 7.9 | N66: 2045 | O66: Bungie | P66: M | Q66: =A66&"|"&B66 -> Halo: Reach|X360
A67: Final Fantasy VII | B67: PS | C67: 1997 | D67: Role-Playing | E67: Sony Computer Entertainment | F67: 3.01 | G67: 2.47 | H67: 3.28 | I67: 0.96 | J67: 9.72 | K67: 92 | L67: 20 | M67: 9.2 | N67: 1282 | O67: SquareSoft | P67: T | Q67: =A67&"|"&B67 -> Final Fantasy VII|PS
A68: Halo 4 | B68: X360 | C68: 2012 | D68: Shooter | E68: Microsoft Game Studios | F68: 6.65 | G68: 2.28 | H68: 0.04 | I68: 0.74 | J68: 9.71 | K68: 87 | L68: 87 | M68: 7 | N68: 3260 | O68: 343 Industries | P68: M | Q68: =A68&"|"&B68 -> Halo 4|X360
A69: Gran Turismo 2 | B69: PS | C69: 1999 | D69: Racing | E69: Sony Computer Entertainment | F69: 3.88 | G69: 3.42 | H69: 1.69 | I69: 0.5 | J69: 9.49 | K69: 93 | L69: 23 | M69: 9 | N69: 135 | O69: Polyphony Digital | P69: T | Q69: =A69&"|"&B69 -> Gran Turismo 2|PS
A70: Just Dance 2 | B70: Wii | C70: 2010 | D70: Misc | E70: Ubisoft | F70: 5.8 | G70: 2.85 | H70: 0.01 | I70: 0.78 | J70: 9.44 | K70: 74 | L70: 24 | M70: 7.3 | N70: 24 | O70: Ubisoft | P70: E10+ | Q70: =A70&"|"&B70 -> Just Dance 2|Wii
A71: Call of Duty: Ghosts | B71: PS3 | C71: 2013 | D71: Shooter | E71: Activision | F71: 4.1 | G71: 3.63 | H71: 0.38 | I71: 1.25 | J71: 9.36 | K71: 71 | L71: 10 | M71: 2.6 | N71: 1047 | O71: Infinity Ward | P71: M | Q71: =A71&"|"&B71 -> Call of Duty: Ghosts|PS3
A72: Call of Duty 4: Modern Warfare | B72: X360 | C72: 2007 | D72: Shooter | E72: Activision | F72: 5.93 | G72: 2.36 | H72: 0.13 | I72: 0.9 | J72: 9.31 | K72: 94 | L72: 70 | M72: 8.4 | N72: 1320 | O72: Infinity Ward | P72: M | Q72: =A72&"|"&B72 -> Call of Duty 4: Modern Warfare|X360
A73: Donkey Kong Country | B73: SNES | C73: 1994 | D73: Platform | E73: Nintendo | F73: 4.36 | G73: 1.71 | H73: 3 | I73: 0.23 | J73: 9.3 | Q73: =A73&"|"&B73 -> Donkey Kong Country|SNES
A74: Minecraft | B74: X360 | C74: 2013 | D74: Misc | E74: Microsoft Game Studios | F74: 5.7 | G74: 2.65 | H74: 0.02 | I74: 0.81 | J74: 9.18 | Q74: =A74&"|"&B74 -> Minecraft|X360
A75: Animal Crossing: New Leaf | B75: 3DS | C75: 2012 | D75: Simulation | E75: Nintendo | F75: 2.03 | G75: 2.36 | H75: 4.39 | I75: 0.39 | J75: 9.16 | K75: 88 | L75: 70 | M75: 8.7 | N75: 626 | O75: Nintendo | P75: E | Q75: =A75&"|"&B75 -> Animal Crossing: New Leaf|3DS
A76: Mario Party DS | B76: DS | C76: 2007 | D76: Misc | E76: Nintendo | F76: 4.4 | G76: 1.85 | H76: 1.98 | I76: 0.68 | J76: 8.91 | K76: 72 | L76: 27 | M76: 7.8 | N76: 85 | O76: Hudson Soft | P76: E | Q76: =A76&"|"&B76 -> Mario Party DS|DS
A77: The Elder Scrolls V: Skyrim | B77: X360 | C77: 2011 | D77: Role-Playing | E77: Bethesda Softworks | F77: 5.05 | G77: 2.79 | H77: 0.1 | I77: 0.85 | J77: 8.79 | K77: 96 | L77: 89 | M77: 8.4 | N77: 3589 | O77: Bethesda Game Studios | P77: M | Q77: =A77&"|"&B77 -> The Elder Scrolls V: Skyrim|X360
A78: Super Mario Kart | B78: SNES | C78: 1992 | D78: Racing | E78: Nintendo | F78: 3.54 | G78: 1.24 | H78: 3.81 | I78: 0.18 | J78: 8.76 | Q78: =A78&"|"&B78 -> Super Mario Kart|SNES
A79: FIFA 16 | B79: PS4 | C79: 2015 | D79: Sports | E79: Electronic Arts | F79: 1.12 | G79: 6.12 | H79: 0.06 | I79: 1.28 | J79: 8.57 | K79: 82 | L79: 42 | M79: 4.3 | N79: 896 | O79: EA Sports | P79: E | Q79: =A79&"|"&B79 -> FIFA 16|PS4
A80: Halo 2 | B80: XB | C80: 2004 | D80: Shooter | E80: Microsoft Game Studios | F80: 6.82 | G80: 1.53 | H80: 0.05 | I80: 0.08 | J80: 8.49 | K80: 95 | L80: 91 | M80: 8.2 | N80: 1218 | O80: Bungie Software | P80: M | Q80: =A80&"|"&B80 -> Halo 2|XB
A81: Wii Party | B81: Wii | C81: 2010 | D81: Misc | E81: Nintendo | F81: 1.75 | G81: 3.47 | H81: 2.49 | I81: 0.67 | J81: 8.38 | K81: 68 | L81: 42 | M81: 7.4 | N81: 54 | O81: Nd Cube | P81: E | Q81: =A81&"|"&B81 -> Wii Party|Wii
A82: Mario Party 8 | B82: Wii | C82: 2007 | D82: Misc | E82: Nintendo | F82: 3.74 | G82: 2.24 | H82: 1.58 | I82: 0.7 | J82: 8.27 | K82: 62 | L82: 41 | M82: 6.3 | N82: 190 | O82: Hudson | P82: E | Q82: =A82&"|"&B82 -> Mario Party 8|Wii
A83: FIFA Soccer 13 | B83: PS3 | C83: 2012 | D83: Action | E83: Electronic Arts | F83: 1.06 | G83: 5.01 | H83: 0.13 | I83: 1.97 | J83: 8.16 | K83: 88 | L83: 37 | M83: 6.6 | N83: 348 | O83: Electronic Arts | P83: E | Q83: =A83&"|"&B83 -> FIFA Soccer 13|PS3
A84: GoldenEye 007 | B84: N64 | C84: 1997 | D84: Shooter | E84: Nintendo | F84: 5.8 | G84: 2.01 | H84: 0.13 | I84: 0.15 | J84: 8.09 | Q84: =A84&"|"&B84 -> GoldenEye 007|N64
A85: Pokemon Black 2/Pokemon White 2 | B85: DS | C85: 2012 | D85: Role-Playing | E85: Nintendo | F85: 2.79 | G85: 1.72 | H85: 3.14 | I85: 0.41 | J85: 8.07 | Q85: =A85&"|"&B85 -> Pokemon Black 2/Pokemon White 2|DS
A86: Final Fantasy X | B86: PS2 | C86: 2001 | D86: Role-Playing | E86: Sony Computer Entertainment | F86: 2.91 | G86: 2.07 | H86: 2.73 | I86: 0.33 | J86: 8.05 | K86: 92 | L86: 53 | M86: 8.7 | N86: 1056 | O86: SquareSoft | P86: T | Q86: =A86&"|"&B86 -> Final Fantasy X|PS2
A87: The Sims 3 | B87: PC | C87: 2009 | D87: Simulation | E87: Electronic Arts | F87: 0.99 | G87: 6.42 | H87: 0 | I87: 0.6 | J87: 8.01 | K87: 86 | L87: 75 | M87: 7.6 | N87: 886 | O87: The Sims Studio | P87: T | Q87: =A87&"|"&B87 -> The Sims 3|PC
A88: Mario & Sonic at the Olympic Games | B88: Wii | C88: 2007 | D88: Sports | E88: Sega | F88: 2.57 | G88: 3.86 | H88: 0.66 | I88: 0.91 | J88: 7.99 | Q88: =A88&"|"&B88 -> Mario & Sonic at the Olympic Games|Wii
A89: Star Wars Battlefront (2015) | B89: PS4 | C89: 2015 | D89: Shooter | E89: Electronic Arts | F89: 2.99 | G89: 3.49 | H89: 0.22 | I89: 1.28 | J89: 7.98 | Q89: =A89&"|"&B89 -> Star Wars Battlefront (2015)|PS4
A90: Final Fantasy VIII | B90: PS | C90: 1999 | D90: Role-Playing | E90: SquareSoft | F90: 2.28 | G90: 1.72 | H90: 3.63 | I90: 0.23 | J90: 7.86 | K90: 90 | L90: 24 | M90: 8.6 | N90: 644 | O90: SquareSoft | P90: T | Q90: =A90&"|"&B90 -> Final Fantasy VIII|PS
A91: Pac-Man | B91: 2600 | C91: 1982 | D91: Puzzle | E91: Atari | F91: 7.28 | G91: 0.45 | H91: 0 | I91: 0.08 | J91: 7.81 | Q91: =A91&"|"&B91 -> Pac-Man|2600
A92: Pokémon Platinum Version | B92: DS | C92: 2008 | D92: Role-Playing | E92: Nintendo | F92: 2.76 | G92: 1.72 | H92: 2.69 | I92: 0.54 | J92: 7.72 | K92: 83 | L92: 46 | M92: 8.5 | N92: 203 | O92: Game Freak | P92: E | Q92: =A92&"|"&B92 -> Pokémon Platinum Version|DS
A93: Grand Theft Auto: Liberty City Stories | B93: PSP | C93: 2005 | D93: Action | E93: Take-Two Interactive | F93: 2.9 | G93: 2.81 | H93: 0.24 | I93: 1.73 | J93: 7.69 | K93: 88 | L93: 65 | M93: 7.6 | N93: 451 | O93: Rockstar Leeds | P93: M | Q93: =A93&"|"&B93 -> Grand Theft Auto: Liberty City Stories|PSP
A94: Call of Duty: Advanced Warfare | B94: PS4 | C94: 2014 | D94: Shooter | E94: Activision | F94: 2.81 | G94: 3.48 | H94: 0.14 | I94: 1.23 | J94: 7.66 | K94: 83 | L94: 39 | M94: 5.7 | N94: 1443 | O94: Sledgehammer Games | P94: M | Q94: =A94&"|"&B94 -> Call of Duty: Advanced Warfare|PS4
A95: The Legend of Zelda: Ocarina of Time | B95: N64 | C95: 1998 | D95: Action | E95: Nintendo | F95: 4.1 | G95: 1.89 | H95: 1.45 | I95: 0.16 | J95: 7.6 | Q95: =A95&"|"&B95 -> The Legend of Zelda: Ocarina of Time|N64
A96: FIFA 17 | B96: PS4 | C96: 2016 | D96: Sports | E96: Electronic Arts | F96: 0.66 | G96: 5.75 | H96: 0.08 | I96: 1.11 | J96: 7.59 | K96: 85 | L96: 41 | M96: 5 | N96: 398 | O96: EA Sports, EA Vancouver | P96: E | Q96: =A96&"|"&B96 -> FIFA 17|PS4
A97: Crash Bandicoot 2: Cortex Strikes Back | B97: PS | C97: 1997 | D97: Platform | E97: Sony Computer Entertainment | F97: 3.78 | G97: 2.17 | H97: 1.31 | I97: 0.31 | J97: 7.58 | Q97: =A97&"|"&B97 -> Crash Bandicoot 2: Cortex Strikes Back|PS
A98: Super Smash Bros. for Wii U and 3DS | B98: 3DS | C98: 2014 | D98: Fighting | E98: Nintendo | F98: 3.27 | G98: 1.37 | H98: 2.43 | I98: 0.48 | J98: 7.55 | Q98: =A98&"|"&B98 -> Super Smash Bros. for Wii U and 3DS|3DS
A99: Super Mario Galaxy 2 | B99: Wii | C99: 2010 | D99: Platform | E99: Nintendo | F99: 3.56 | G99: 2.35 | H99: 0.98 | I99: 0.62 | J99: 7.51 | K99: 97 | L99: 87 | M99: 9.1 | N99: 1854 | O99: Nintendo EAD Tokyo | P99: E | Q99: =A99&"|"&B99 -> Super Mario Galaxy 2|Wii
A100: Super Mario Bros. 2 | B100: NES | C100: 1988 | D100: Platform | E100: Nintendo | F100: 5.39 | G100: 1.18 | H100: 0.7 | I100: 0.19 | J100: 7.46 | Q100: =A100&"|"&B100 -> Super Mario Bros. 2|NES
...

Sheet Game Lookup
A1: GAME LOOKUP TOOL
A2: Type a game title and platform below. Numeric fields use SUMIFS; text fields use INDEX/MATCH.
B4: Game Title: | C4: Wii Sports
B5: Platform: | C5: Wii
B7: Field | C7: Value
B8: Genre | C8: =IFERROR(INDEX('Raw Data'!$D:$D,MATCH($C$4&"|"&$C$5,'Raw Data'!$Q:$Q,0)),"Not found") -> Sports
B9: Publisher | C9: =IFERROR(INDEX('Raw Data'!$E:$E,MATCH($C$4&"|"&$C$5,'Raw Data'!$Q:$Q,0)),"Not found") -> Nintendo
B10: Developer | C10: =IFERROR(INDEX('Raw Data'!$O:$O,MATCH($C$4&"|"&$C$5,'Raw Data'!$Q:$Q,0)),"Not found") -> Nintendo
B11: Rating | C11: =IFERROR(INDEX('Raw Data'!$P:$P,MATCH($C$4&"|"&$C$5,'Raw Data'!$Q:$Q,0)),"Not found") -> E
B12: Year of Release | C12: =IF(COUNTIFS('Raw Data'!$A:$A,$C$4,'Raw Data'!$B:$B,$C$5,'Raw Data'!$C:$C,"<>")=0,"No data",SUMIFS('Raw Data'!$C:$C,'Raw Data'!$A:$A,$C$4,'Raw Data'!$B:$B,$C$5)) -> 2006
B13: NA Sales ($M) | C13: =IF(COUNTIFS('Raw Data'!$A:$A,$C$4,'Raw Data'!$B:$B,$C$5,'Raw Data'!$F:$F,"<>")=0,"No data",SUMIFS('Raw Data'!$F:$F,'Raw Data'!$A:$A,$C$4,'Raw Data'!$B:$B,$C$5)) -> 41.36
B14: EU Sales ($M) | C14: =IF(COUNTIFS('Raw Data'!$A:$A,$C$4,'Raw Data'!$B:$B,$C$5,'Raw Data'!$G:$G,"<>")=0,"No data",SUMIFS('Raw Data'!$G:$G,'Raw Data'!$A:$A,$C$4,'Raw Data'!$B:$B,$C$5)) -> 28.96
B15: JP Sales ($M) | C15: =IF(COUNTIFS('Raw Data'!$A:$A,$C$4,'Raw Data'!$B:$B,$C$5,'Raw Data'!$H:$H,"<>")=0,"No data",SUMIFS('Raw Data'!$H:$H,'Raw Data'!$A:$A,$C$4,'Raw Data'!$B:$B,$C$5)) -> 3.77
B16: Other Sales ($M) | C16: =IF(COUNTIFS('Raw Data'!$A:$A,$C$4,'Raw Data'!$B:$B,$C$5,'Raw Data'!$I:$I,"<>")=0,"No data",SUMIFS('Raw Data'!$I:$I,'Raw Data'!$A:$A,$C$4,'Raw Data'!$B:$B,$C$5)) -> 8.45
B17: Global Sales ($M) | C17: =IF(COUNTIFS('Raw Data'!$A:$A,$C$4,'Raw Data'!$B:$B,$C$5,'Raw Data'!$J:$J,"<>")=0,"No data",SUMIFS('Raw Data'!$J:$J,'Raw Data'!$A:$A,$C$4,'Raw Data'!$B:$B,$C$5)) -> 82.53
B18: Critic Score | C18: =IF(COUNTIFS('Raw Data'!$A:$A,$C$4,'Raw Data'!$B:$B,$C$5,'Raw Data'!$K:$K,"<>")=0,"No data",SUMIFS('Raw Data'!$K:$K,'Raw Data'!$A:$A,$C$4,'Raw Data'!$B:$B,$C$5)) -> 76
B19: Critic Count | C19: =IF(COUNTIFS('Raw Data'!$A:$A,$C$4,'Raw Data'!$B:$B,$C$5,'Raw Data'!$L:$L,"<>")=0,"No data",SUMIFS('Raw Data'!$L:$L,'Raw Data'!$A:$A,$C$4,'Raw Data'!$B:$B,$C$5)) -> 51
B20: User Score | C20: =IF(COUNTIFS('Raw Data'!$A:$A,$C$4,'Raw Data'!$B:$B,$C$5,'Raw Data'!$M:$M,"<>")=0,"No data",SUMIFS('Raw Data'!$M:$M,'Raw Data'!$A:$A,$C$4,'Raw Data'!$B:$B,$C$5)) -> 8
B21: User Count | C21: =IF(COUNTIFS('Raw Data'!$A:$A,$C$4,'Raw Data'!$B:$B,$C$5,'Raw Data'!$N:$N,"<>")=0,"No data",SUMIFS('Raw Data'!$N:$N,'Raw Data'!$A:$A,$C$4,'Raw Data'!$B:$B,$C$5)) -> 322

Sheet Genre Insights
A1: GENRE INSIGHTS
A2: Critical reception vs. commercial performance, by genre.
A4: Genre | B4: Games | C4: Total Global Sales ($M) | D4: Avg Critic Score | E4: Avg User Score (x10) | F4: Best Seller | H4: Filter
A5: Action | B5: =COUNTIF('Raw Data'!$D:$D,$A5) -> 3370 | C5: =SUMIF('Raw Data'!$D:$D,$A5,'Raw Data'!$J:$J) -> 1745.27 | D5: =AVERAGEIFS('Raw Data'!$K:$K,'Raw Data'!$D:$D,$A5) -> 66.629101 | E5: =AVERAGEIFS('Raw Data'!$M:$M,'Raw Data'!$D:$D,$A5)*10 -> 70.540437 | F5: =IFERROR(INDEX('Raw Data'!$A:$A,SUMPRODUCT(('Raw Data'!$D$2:$D$16718=$A5)*('Raw Data'!$J$2:$J$16718=_xlfn.MAXIFS('Raw Data'!$J$2:$J$16718,'Raw Data'!$D$2:$D$16718,$A5))*ROW('Raw Data'!$D$2:$D$16718))),"N/A") -> Grand Theft Auto V
A6: Adventure | B6: =COUNTIF('Raw Data'!$D:$D,$A6) -> 1303 | C6: =SUMIF('Raw Data'!$D:$D,$A6,'Raw Data'!$J:$J) -> 237.69 | D6: =AVERAGEIFS('Raw Data'!$K:$K,'Raw Data'!$D:$D,$A6) -> 65.331269 | E6: =AVERAGEIFS('Raw Data'!$M:$M,'Raw Data'!$D:$D,$A6)*10 -> 71.33 | F6: =IFERROR(INDEX('Raw Data'!$A:$A,SUMPRODUCT(('Raw Data'!$D$2:$D$16718=$A6)*('Raw Data'!$J$2:$J$16718=_xlfn.MAXIFS('Raw Data'!$J$2:$J$16718,'Raw Data'!$D$2:$D$16718,$A6))*ROW('Raw Data'!$D$2:$D$16718))),"N/A") -> Super Mario Land 2: 6 Golden Coins | H6: Sum - Global_Sales | I6: Rating
A7: Fighting | B7: =COUNTIF('Raw Data'!$D:$D,$A7) -> 849 | C7: =SUMIF('Raw Data'!$D:$D,$A7,'Raw Data'!$J:$J) -> 447.48 | D7: =AVERAGEIFS('Raw Data'!$K:$K,'Raw Data'!$D:$D,$A7) -> 69.217604 | E7: =AVERAGEIFS('Raw Data'!$M:$M,'Raw Data'!$D:$D,$A7)*10 -> 73.025063 | F7: =IFERROR(INDEX('Raw Data'!$A:$A,SUMPRODUCT(('Raw Data'!$D$2:$D$16718=$A7)*('Raw Data'!$J$2:$J$16718=_xlfn.MAXIFS('Raw Data'!$J$2:$J$16718,'Raw Data'!$D$2:$D$16718,$A7))*ROW('Raw Data'!$D$2:$D$16718))),"N/A") -> Super Smash Bros. Brawl | H7: Genre | I7: AO | J7: E | K7: E10+ | L7: EC | M7: K-A | N7: M | O7: RP | P7: T | Q7: (empty) | R7: Total Result
A8: Misc | B8: =COUNTIF('Raw Data'!$D:$D,$A8) -> 1750 | C8: =SUMIF('Raw Data'!$D:$D,$A8,'Raw Data'!$J:$J) -> 803.18 | D8: =AVERAGEIFS('Raw Data'!$K:$K,'Raw Data'!$D:$D,$A8) -> 66.619503 | E8: =AVERAGEIFS('Raw Data'!$M:$M,'Raw Data'!$D:$D,$A8)*10 -> 68.193622 | F8: =IFERROR(INDEX('Raw Data'!$A:$A,SUMPRODUCT(('Raw Data'!$D$2:$D$16718=$A8)*('Raw Data'!$J$2:$J$16718=_xlfn.MAXIFS('Raw Data'!$J$2:$J$16718,'Raw Data'!$D$2:$D$16718,$A8))*ROW('Raw Data'!$D$2:$D$16718))),"N/A") -> Wii Play | H8: Action | I8: 1.95 | J8: 198.44 | K8: 219.04 | L8: 0.45 | N8: 601.82 | P8: 333.76 | Q8: 389.81 | R8: 1745.27
A9: Platform | B9: =COUNTIF('Raw Data'!$D:$D,$A9) -> 888 | C9: =SUMIF('Raw Data'!$D:$D,$A9,'Raw Data'!$J:$J) -> 828.08 | D9: =AVERAGEIFS('Raw Data'!$K:$K,'Raw Data'!$D:$D,$A9) -> 68.05835 | E9: =AVERAGEIFS('Raw Data'!$M:$M,'Raw Data'!$D:$D,$A9)*10 -> 73.014019 | F9: =IFERROR(INDEX('Raw Data'!$A:$A,SUMPRODUCT(('Raw Data'!$D$2:$D$16718=$A9)*('Raw Data'!$J$2:$J$16718=_xlfn.MAXIFS('Raw Data'!$J$2:$J$16718,'Raw Data'!$D$2:$D$16718,$A9))*ROW('Raw Data'!$D$2:$D$16718))),"N/A") -> Super Mario Bros. | H9: Adventure | J9: 58.01 | K9: 11.73 | L9: 0.36 | N9: 42.15 | P9: 19.34 | Q9: 106.1 | R9: 237.69
A10: Puzzle | B10: =COUNTIF('Raw Data'!$D:$D,$A10) -> 580 | C10: =SUMIF('Raw Data'!$D:$D,$A10,'Raw Data'!$J:$J) -> 243.02 | D10: =AVERAGEIFS('Raw Data'!$K:$K,'Raw Data'!$D:$D,$A10) -> 67.424107 | E10: =AVERAGEIFS('Raw Data'!$M:$M,'Raw Data'!$D:$D,$A10)*10 -> 71.75 | F10: =IFERROR(INDEX('Raw Data'!$A:$A,SUMPRODUCT(('Raw Data'!$D$2:$D$16718=$A10)*('Raw Data'!$J$2:$J$16718=_xlfn.MAXIFS('Raw Data'!$J$2:$J$16718,'Raw Data'!$D$2:$D$16718,$A10))*ROW('Raw Data'!$D$2:$D$16718))),"N/A") -> Tetris | H10: Fighting | J10: 1.09 | K10: 4.56 | N10: 28.8 | P10: 226.59 | Q10: 186.44 | R10: 447.48
A11: Racing | B11: =COUNTIF('Raw Data'!$D:$D,$A11) -> 1249 | C11: =SUMIF('Raw Data'!$D:$D,$A11,'Raw Data'!$J:$J) -> 728.9 | D11: =AVERAGEIFS('Raw Data'!$K:$K,'Raw Data'!$D:$D,$A11) -> 67.963612 | E11: =AVERAGEIFS('Raw Data'!$M:$M,'Raw Data'!$D:$D,$A11)*10 -> 70.361934 | F11: =IFERROR(INDEX('Raw Data'!$A:$A,SUMPRODUCT(('Raw Data'!$D$2:$D$16718=$A11)*('Raw Data'!$J$2:$J$16718=_xlfn.MAXIFS('Raw Data'!$J$2:$J$16718,'Raw Data'!$D$2:$D$16718,$A11))*ROW('Raw Data'!$D$2:$D$16718))),"N/A") -> Mario Kart Wii | H11: Misc | J11: 289.39 | K11: 115.13 | L11: 0.97 | M11: 1.92 | N11: 3.48 | P11: 129.78 | Q11: 262.51 | R11: 803.18
A12: Role-Playing | B12: =COUNTIF('Raw Data'!$D:$D,$A12) -> 1500 | C12: =SUMIF('Raw Data'!$D:$D,$A12,'Raw Data'!$J:$J) -> 934.4 | D12: =AVERAGEIFS('Raw Data'!$K:$K,'Raw Data'!$D:$D,$A12) -> 72.652646 | E12: =AVERAGEIFS('Raw Data'!$M:$M,'Raw Data'!$D:$D,$A12)*10 -> 76.195155 | F12: =IFERROR(INDEX('Raw Data'!$A:$A,SUMPRODUCT(('Raw Data'!$D$2:$D$16718=$A12)*('Raw Data'!$J$2:$J$16718=_xlfn.MAXIFS('Raw Data'!$J$2:$J$16718,'Raw Data'!$D$2:$D$16718,$A12))*ROW('Raw Data'!$D$2:$D$16718))),"N/A") -> Pokemon Red/Pokemon Blue | H12: Platform | J12: 329.8 | K12: 60.63 | N12: 1.6 | P12: 23.73 | Q12: 412.32 | R12: 828.08
A13: Shooter | B13: =COUNTIF('Raw Data'!$D:$D,$A13) -> 1323 | C13: =SUMIF('Raw Data'!$D:$D,$A13,'Raw Data'!$J:$J) -> 1052.94 | D13: =AVERAGEIFS('Raw Data'!$K:$K,'Raw Data'!$D:$D,$A13) -> 70.181144 | E13: =AVERAGEIFS('Raw Data'!$M:$M,'Raw Data'!$D:$D,$A13)*10 -> 70.418831 | F13: =IFERROR(INDEX('Raw Data'!$A:$A,SUMPRODUCT(('Raw Data'!$D$2:$D$16718=$A13)*('Raw Data'!$J$2:$J$16718=_xlfn.MAXIFS('Raw Data'!$J$2:$J$16718,'Raw Data'!$D$2:$D$16718,$A13))*ROW('Raw Data'!$D$2:$D$16718))),"N/A") -> Duck Hunt | H13: Puzzle | J13: 88.18 | K13: 22.33 | P13: 2.51 | Q13: 130 | R13: 243.02
A14: Simulation | B14: =COUNTIF('Raw Data'!$D:$D,$A14) -> 874 | C14: =SUMIF('Raw Data'!$D:$D,$A14,'Raw Data'!$J:$J) -> 390.42 | D14: =AVERAGEIFS('Raw Data'!$K:$K,'Raw Data'!$D:$D,$A14) -> 68.619318 | E14: =AVERAGEIFS('Raw Data'!$M:$M,'Raw Data'!$D:$D,$A14)*10 -> 71.34593 | F14: =IFERROR(INDEX('Raw Data'!$A:$A,SUMPRODUCT(('Raw Data'!$D$2:$D$16718=$A14)*('Raw Data'!$J$2:$J$16718=_xlfn.MAXIFS('Raw Data'!$J$2:$J$16718,'Raw Data'!$D$2:$D$16718,$A14))*ROW('Raw Data'!$D$2:$D$16718))),"N/A") -> Nintendogs | H14: Racing | J14: 369.74 | K14: 56.2 | N14: 4.97 | O14: 0.01 | P14: 96.53 | Q14: 201.45 | R14: 728.9
A15: Sports | B15: =COUNTIF('Raw Data'!$D:$D,$A15) -> 2348 | C15: =SUMIF('Raw Data'!$D:$D,$A15,'Raw Data'!$J:$J) -> 1332 | D15: =AVERAGEIFS('Raw Data'!$K:$K,'Raw Data'!$D:$D,$A15) -> 71.968174 | E15: =AVERAGEIFS('Raw Data'!$M:$M,'Raw Data'!$D:$D,$A15)*10 -> 69.611967 | F15: =IFERROR(INDEX('Raw Data'!$A:$A,SUMPRODUCT(('Raw Data'!$D$2:$D$16718=$A15)*('Raw Data'!$J$2:$J$16718=_xlfn.MAXIFS('Raw Data'!$J$2:$J$16718,'Raw Data'!$D$2:$D$16718,$A15))*ROW('Raw Data'!$D$2:$D$16718))),"N/A") -> Wii Sports | H15: Role-Playing | J15: 70.48 | K15: 50.48 | N15: 153.87 | P15: 239.49 | Q15: 420.08 | R15: 934.4
A16: Strategy | B16: =COUNTIF('Raw Data'!$D:$D,$A16) -> 683 | C16: =SUMIF('Raw Data'!$D:$D,$A16,'Raw Data'!$J:$J) -> 174.5 | D16: =AVERAGEIFS('Raw Data'!$K:$K,'Raw Data'!$D:$D,$A16) -> 72.086093 | E16: =AVERAGEIFS('Raw Data'!$M:$M,'Raw Data'!$D:$D,$A16)*10 -> 72.951768 | F16: =IFERROR(INDEX('Raw Data'!$A:$A,SUMPRODUCT(('Raw Data'!$D$2:$D$16718=$A16)*('Raw Data'!$J$2:$J$16718=_xlfn.MAXIFS('Raw Data'!$J$2:$J$16718,'Raw Data'!$D$2:$D$16718,$A16))*ROW('Raw Data'!$D$2:$D$16718))),"N/A") -> Pokemon Stadium | H16: Shooter | J16: 4.32 | K16: 20.84 | N16: 626.55 | P16: 200.47 | Q16: 200.76 | R16: 1052.94
H17: Simulation | J17: 160.74 | K17: 21.85 | N17: 1.32 | P17: 93.28 | Q17: 113.23 | R17: 390.42
H18: Sports | J18: 845.87 | K18: 53.66 | N18: 3.91 | P18: 94.86 | Q18: 333.7 | R18: 1332
H19: Strategy | J19: 20.84 | K19: 19.36 | M19: 2.41 | N19: 5.37 | O19: 0.07 | P19: 34.06 | Q19: 92.39 | R19: 174.5
H20: Total Result | I20: 1.95 | J20: 2436.9 | K20: 655.81 | L20: 1.78 | M20: 4.33 | N20: 1473.84 | O20: 0.08 | P20: 1494.4 | Q20: 2848.79 | R20: 8917.88

Sheet Sales Trends
A1: INDUSTRY SALES TRENDS
A2: Years with healthy sample sizes only (1996-2016); 2017+ rows are residual/incomplete.
A4: Year | B4: Releases | C4: Total Global Sales ($M) | D4: Avg Critic Score
A5: 1996 | B5: =COUNTIF('Raw Data'!$C:$C,$A5) -> 263 | C5: =SUMIF('Raw Data'!$C:$C,$A5,'Raw Data'!$J:$J) -> 199.15 | D5: =AVERAGEIFS('Raw Data'!$K:$K,'Raw Data'!$C:$C,$A5) -> 89.875
A6: 1997 | B6: =COUNTIF('Raw Data'!$C:$C,$A6) -> 289 | C6: =SUMIF('Raw Data'!$C:$C,$A6,'Raw Data'!$J:$J) -> 200.98 | D6: =AVERAGEIFS('Raw Data'!$K:$K,'Raw Data'!$C:$C,$A6) -> 85.294118
A7: 1998 | B7: =COUNTIF('Raw Data'!$C:$C,$A7) -> 379 | C7: =SUMIF('Raw Data'!$C:$C,$A7,'Raw Data'!$J:$J) -> 256.45 | D7: =AVERAGEIFS('Raw Data'!$K:$K,'Raw Data'!$C:$C,$A7) -> 81.821429
A8: 1999 | B8: =COUNTIF('Raw Data'!$C:$C,$A8) -> 338 | C8: =SUMIF('Raw Data'!$C:$C,$A8,'Raw Data'!$J:$J) -> 251.25 | D8: =AVERAGEIFS('Raw Data'!$K:$K,'Raw Data'!$C:$C,$A8) -> 75.769231
A9: 2000 | B9: =COUNTIF('Raw Data'!$C:$C,$A9) -> 350 | C9: =SUMIF('Raw Data'!$C:$C,$A9,'Raw Data'!$J:$J) -> 201.58 | D9: =AVERAGEIFS('Raw Data'!$K:$K,'Raw Data'!$C:$C,$A9) -> 69.34965
A10: 2001 | B10: =COUNTIF('Raw Data'!$C:$C,$A10) -> 482 | C10: =SUMIF('Raw Data'!$C:$C,$A10,'Raw Data'!$J:$J) -> 331.47 | D10: =AVERAGEIFS('Raw Data'!$K:$K,'Raw Data'!$C:$C,$A10) -> 71.41411
A11: 2002 | B11: =COUNTIF('Raw Data'!$C:$C,$A11) -> 829 | C11: =SUMIF('Raw Data'!$C:$C,$A11,'Raw Data'!$J:$J) -> 395.51 | D11: =AVERAGEIFS('Raw Data'!$K:$K,'Raw Data'!$C:$C,$A11) -> 69.046252
A12: 2003 | B12: =COUNTIF('Raw Data'!$C:$C,$A12) -> 775 | C12: =SUMIF('Raw Data'!$C:$C,$A12,'Raw Data'!$J:$J) -> 357.8 | D12: =AVERAGEIFS('Raw Data'!$K:$K,'Raw Data'!$C:$C,$A12) -> 70.181197
A13: 2004 | B13: =COUNTIF('Raw Data'!$C:$C,$A13) -> 762 | C13: =SUMIF('Raw Data'!$C:$C,$A13,'Raw Data'!$J:$J) -> 419.05 | D13: =AVERAGEIFS('Raw Data'!$K:$K,'Raw Data'!$C:$C,$A13) -> 69.393939
A14: 2005 | B14: =COUNTIF('Raw Data'!$C:$C,$A14) -> 939 | C14: =SUMIF('Raw Data'!$C:$C,$A14,'Raw Data'!$J:$J) -> 458.31 | D14: =AVERAGEIFS('Raw Data'!$K:$K,'Raw Data'!$C:$C,$A14) -> 68.819847
A15: 2006 | B15: =COUNTIF('Raw Data'!$C:$C,$A15) -> 1006 | C15: =SUMIF('Raw Data'!$C:$C,$A15,'Raw Data'!$J:$J) -> 518.22 | D15: =AVERAGEIFS('Raw Data'!$K:$K,'Raw Data'!$C:$C,$A15) -> 67.33871
A16: 2007 | B16: =COUNTIF('Raw Data'!$C:$C,$A16) -> 1197 | C16: =SUMIF('Raw Data'!$C:$C,$A16,'Raw Data'!$J:$J) -> 605.37 | D16: =AVERAGEIFS('Raw Data'!$K:$K,'Raw Data'!$C:$C,$A16) -> 66.180636
... A25: 2016 | B25: =COUNTIF('Raw Data'!$C:$C,$A25) -> 502 | C25: =SUMIF('Raw Data'!$C:$C,$A25,'Raw Data'!$J:$J) -> 130.1 | D25: =AVERAGEIFS('Raw Data'!$K:$K,'Raw Data'!$C:$C,$A25) -> 73.155172
A27: Top Publishers by Total Global Sales
A28: Publisher | B28: Games | C28: Total Global Sales ($M) | D28: Avg Sales / Game
A29: Nintendo | B29: =COUNTIF('Raw Data'!$E:$E,$A29) -> 706 | C29: =SUMIF('Raw Data'!$E:$E,$A29,'Raw Data'!$J:$J) -> 1788.81 | D29: =IF(B29=0,0,C29/B29) -> 2.5337252
A30: Electronic Arts | B30: =COUNTIF('Raw Data'!$E:$E,$A30) -> 1356 | C30: =SUMIF('Raw Data'!$E:$E,$A30,'Raw Data'!$J:$J) -> 1116.96 | D30: =IF(B30=0,0,C30/B30) -> 0.82371681
A31: Activision | B31: =COUNTIF('Raw Data'!$E:$E,$A31) -> 985 | C31: =SUMIF('Raw Data'!$E:$E,$A31,'Raw Data'!$J:$J) -> 731.16 | D31: =IF(B31=0,0,C31/B31) -> 0.74229442
A32: Sony Computer Entertainment | B32: =COUNTIF('Raw Data'!$E:$E,$A32) -> 687 | C32: =SUMIF('Raw Data'!$E:$E,$A32,'Raw Data'!$J:$J) -> 606.48 | D32: =IF(B32=0,0,C32/B32) -> 0.88279476
A33: Ubisoft | B33: =COUNTIF('Raw Data'!$E:$E,$A33) -> 933 | C33: =SUMIF('Raw Data'!$E:$E,$A33,'Raw Data'!$J:$J) -> 471.61 | D33: =IF(B33=0,0,C33/B33) -> 0.50547696
A34: Take-Two Interactive | B34: =COUNTIF('Raw Data'!$E:$E,$A34) -> 422 | C34: =SUMIF('Raw Data'!$E:$E,$A34,'Raw Data'!$J:$J) -> 403.82 | D34: =IF(B34=0,0,C34/B34) -> 0.95691943
A35: THQ | B35: =COUNTIF('Raw Data'!$E:$E,$A35) -> 715 | C35: =SUMIF('Raw Data'!$E:$E,$A35,'Raw Data'!$J:$J) -> 338.44 | D35: =IF(B35=0,0,C35/B35) -> 0.47334266
A36: Konami Digital Entertainment | B36: =COUNTIF('Raw Data'!$E:$E,$A36) -> 834 | C36: =SUMIF('Raw Data'!$E:$E,$A36,'Raw Data'!$J:$J) -> 282.39 | D36: =IF(B36=0,0,C36/B36) -> 0.33859712
A37: Sega | B37: =COUNTIF('Raw Data'!$E:$E,$A37) -> 638 | C37: =SUMIF('Raw Data'!$E:$E,$A37,'Raw Data'!$J:$J) -> 270.35 | D37: =IF(B37=0,0,C37/B37) -> 0.42374608
A38: Namco Bandai Games | B38: =COUNTIF('Raw Data'!$E:$E,$A38) -> 939 | C38: =SUMIF('Raw Data'!$E:$E,$A38,'Raw Data'!$J:$J) -> 254.62 | D38: =IF(B38=0,0,C38/B38) -> 0.27116081
